{
   "widgets": [
      {
         "type": "chart",
         "gridPos": {
            "h": 13,
            "w": 12,
            "x": 0,
            "y": 0
         },
         "series": [
            {
               "name": "temperature",
               "sourceNames": [
                  "temperature"
               ],
               "formula": "",
               "options": {
                  "_serie": "temperature",
                  "stroke": "rgba(231,76,60,1)",
                  "fill": "rgba(231,76,60,0.1)"
               },
               "type": "number"
            },
            {
               "name": "tempOut",
               "sourceNames": [
                  "tempOut"
               ],
               "formula": "",
               "options": {
                  "_serie": "tempOut",
                  "stroke": "rgba(52,152,219,1)",
                  "fill": "rgba(52,152,219,0.1)"
               },
               "type": "number"
            },
            {
               "name": "tempOutRaw",
               "sourceNames": [
                  "tempOutRaw"
               ],
               "formula": "",
               "options": {
                  "_serie": "tempOutRaw",
                  "stroke": "rgba(46,204,113,1)",
                  "fill": "rgba(46,204,113,0.1)"
               },
               "type": "number"
            }
         ]
      }
   ],
   "viewDuration": "300"
}